{"id": "fbur4w", "title": "Python Syntax Flowchart (for beginners)", "url": "https://www.reddit.com/r/learnpython/comments/fbur4w/python_syntax_flowchart_for_beginners/", "subreddit": "learnpython", "author": "t2_4eyzwkvw", "text": "Hi all, someone had shared a very helpful flow chart that outlined the structure and differences between python...things, including objects, functions, classes, etc. I understand there were some criticisms, but found it helpful to remind me of the syntax structure. Would be forever grateful if someone could share again!", "comments": [{"id": "fj74nk8", "author": "nqthqn2", "body": "This? https://raw.githubusercontent.com/coodict/python3-in-one-pic/master/py3%20in%20one%20pic.png"}]}